AUTHORS
LICENSE
MANIFEST.in
README.markdown
setup.py
django_error_pages.egg-info/PKG-INFO
django_error_pages.egg-info/SOURCES.txt
django_error_pages.egg-info/dependency_links.txt
django_error_pages.egg-info/not-zip-safe
django_error_pages.egg-info/top_level.txt
error_pages/__init__.py
error_pages/config.py
error_pages/http.py
error_pages/middleware.py
error_pages/template.py
error_pages/views.py