Metadata-Version: 1.0
Name: django-error-pages
Version: 0.4
Summary: Use any HTTP error status with Django.
Home-page: https://github.com/Roejames12/django-error-pages/
Author: James Roe
Author-email: roejames12@hotmail.com
License: GNU General Public License (GPL)
Platform: UNKNOWN
Classifier: Development Status :: 4 - Beta
Classifier: Framework :: Django
Classifier: Intended Audience :: Developers
Classifier: License :: OSI Approved :: GNU General Public License (GPL)
Classifier: Operating System :: OS Independent
Classifier: Programming Language :: Python
Classifier: Topic :: Internet :: WWW/HTTP
